mdm/__init__.py
mdm/mdm.py
md_preview022-1.0.0.dist-info/LICENSE
md_preview022-1.0.0.dist-info/METADATA
md_preview022-1.0.0.dist-info/WHEEL
md_preview022-1.0.0.dist-info/entry_points.txt
md_preview022-1.0.0.dist-info/top_level.txt
md_preview022-1.0.0.dist-info/RECORD
