Metadata-Version: 2.1
Name: md-preview022
Version: 1.0.0
Summary: A simple Markdown preview tool for the terminal.
Home-page: https://github.com/akaashvaa/preview_md_file
Author: Akash Verma
Author-email: ahmvaad@gmail.com
License: UNKNOWN
Platform: UNKNOWN
Classifier: Programming Language :: Python :: 3
Classifier: License :: OSI Approved :: MIT License
Classifier: Operating System :: OS Independent
Requires-Python: >=3.6
License-File: LICENSE
Requires-Dist: markdown
Requires-Dist: rich
